{"cameraMode":{"drawMode":0,"name":"Shaded","section":"Shading Mode"},"sceneLighting":false,"audioPlay":false,"sceneViewState":{"m_AlwaysRefresh":false,"showFog":true,"showSkybox":false,"showFlares":true,"showImageEffects":true,"showParticleSystems":true,"showVisualEffectGraphs":true,"m_FxEnabled":true},"in2DMode":false,"pivot":{"x":0.06858828663825989,"y":-0.10692954063415528,"z":0.08872416615486145},"rotation":{"x":-0.020632902160286905,"y":-0.9770318865776062,"z":-0.11186694353818894,"w":0.18021228909492494},"size":0.3043222427368164,"orthographic":false}